poisonlib/__init__.py
poisonlib/partitioners/DummyPartitioner.py
poisonlib/partitioners/partition.py
poisonlib/poisoners/KNNPoisoner.py
poisonlib-0.1.0.dist-info/WHEEL
poisonlib-0.1.0.dist-info/METADATA
poisonlib-0.1.0.dist-info/RECORD
