Metadata-Version: 2.1
Name: poisonlib
Version: 0.1.0
Summary: A library for algorithmic poisoning of machine learning datasets
License: MIT
Author: srthiru
Author-email: srthiruvenkadam@gmail.com
Requires-Python: >=3.8,<4.0
Classifier: License :: OSI Approved :: MIT License
Classifier: Programming Language :: Python :: 3
Classifier: Programming Language :: Python :: 3.10
Classifier: Programming Language :: Python :: 3.8
Classifier: Programming Language :: Python :: 3.9
Requires-Dist: numpy (>=1.22.2,<2.0.0)
Requires-Dist: scipy (>=1.7.3,<2.0.0)
Requires-Dist: sklearn (>=0.0,<0.1)
